llama_index/readers/pdf_marker/__init__.py
llama_index/readers/pdf_marker/base.py
llama_index_readers_pdf_marker-0.4.1.dist-info/METADATA
llama_index_readers_pdf_marker-0.4.1.dist-info/WHEEL
llama_index_readers_pdf_marker-0.4.1.dist-info/licenses/LICENSE
llama_index_readers_pdf_marker-0.4.1.dist-info/RECORD
