Metadata-Version: 2.4
Name: llama-index-readers-pdf-marker
Version: 0.4.1
Summary: llama-index readers marker integration
Author-email: Nathan LENAS <nathan.lenas@lmddc.lu>
License-Expression: GPL-3.0-or-later
License-File: LICENSE
Requires-Python: <4.0,>=3.9
Requires-Dist: llama-index-core<0.15,>=0.13.0
Requires-Dist: marker-pdf<0.3,>=0.2.0
